anson/__init__.py
anson/io/__init__.py
anson/io/odysz/__init__.py
anson/io/odysz/anson.py
anson/io/odysz/common.py
anson/io/odysz/utils.py
anson/io/odysz/version.py
anson_py3-0.4.3.dist-info/METADATA
anson_py3-0.4.3.dist-info/WHEEL
anson_py3-0.4.3.dist-info/licenses/LICENSE
anson_py3-0.4.3.dist-info/RECORD
