Metadata-Version: 2.4
Name: anson.py3
Version: 0.4.3
Summary: Anson for Python3
Project-URL: Homepage, https://github.com/odys-z/antson/py3
Project-URL: Issues, https://github.com/odys-z/antson/issues
Author-email: Ody Z <odys.zhou@gmail.com>
License: Copyright (c) 2025 Ody Z. All rights reserved.
License-File: LICENSE
Classifier: Operating System :: OS Independent
Classifier: Programming Language :: Python :: 3
Requires-Python: >=3.9
Requires-Dist: importlib
Requires-Dist: requests
Requires-Dist: typing-extensions>=4.0.0
Provides-Extra: testing
Requires-Dist: pytest; extra == 'testing'
Requires-Dist: requests; extra == 'testing'
Requires-Dist: semantics-py3; extra == 'testing'
